pago_facil_sdk/__init__.py
pago_facil_sdk/pago_facil.py
pago_facil_sdk-0.1.dist-info/METADATA
pago_facil_sdk-0.1.dist-info/WHEEL
pago_facil_sdk-0.1.dist-info/top_level.txt
pago_facil_sdk-0.1.dist-info/RECORD
