Metadata-Version: 2.1
Name: pago-facil-sdk
Version: 0.1
Summary: SDK for Pago Online
Home-page: https://github.com/javatechy/dokr
Author: Luis Cruz
Author-email: luis.cruz@gmail.com
License: UNKNOWN
Platform: UNKNOWN
Classifier: Programming Language :: Python :: 3
Classifier: License :: OSI Approved :: MIT License
Classifier: Operating System :: OS Independent
